metadict/__about__.py
metadict/__init__.py
metadict/metadict.py
metadict-0.1.3.dist-info/LICENSE
metadict-0.1.3.dist-info/METADATA
metadict-0.1.3.dist-info/WHEEL
metadict-0.1.3.dist-info/top_level.txt
metadict-0.1.3.dist-info/RECORD
