Metadata-Version: 2.1
Name: metadict
Version: 0.1.3
Summary: MetaDict is a powerful dict subclass enabling (nested) attribute-style item access/assignment and IDE autocompletion support.
Home-page: https://github.com/LarsHill/metadict/
Author: Lars Hillebrand
Author-email: hokage555@web.de
License: Apache-2.0
Download-URL: https://github.com/LarsHill/metadict/
Keywords: dict,attribute-style syntax,nesting,auto-completion
Platform: UNKNOWN
Requires-Python: >=3.6
Provides-Extra: tests
Requires-Dist: pytest ; extra == 'tests'
